LICENSE
MANIFEST.in
README.org
setup.cfg
setup.py
hgl/__init__.py
hgl/engine.py
hgl/settings.py
hgl.egg-info/PKG-INFO
hgl.egg-info/SOURCES.txt
hgl.egg-info/dependency_links.txt
hgl.egg-info/requires.txt
hgl.egg-info/top_level.txt
hgl/calculate/__init__.py
hgl/calculate/angle.py
hgl/calculate/box.py
hgl/calculate/camera.py
hgl/calculate/circle.py
hgl/calculate/curve.py
hgl/calculate/distance.py
hgl/calculate/font_outline.py
hgl/calculate/grid.py
hgl/calculate/line.py
hgl/calculate/misc.py
hgl/calculate/numpy_structures.py
hgl/calculate/origin.py
hgl/calculate/point.py
hgl/calculate/polygon.py
hgl/calculate/triangle.py
hgl/context/__init__.py
hgl/context/glut_context.py
hgl/context/gtkglarea_context.py
hgl/context/kivy_context.py
hgl/context/pygame_context.py
hgl/context/sdl2_context.py
hgl/context/template.py
hgl/helpers/__init__.py
hgl/helpers/context.py
hgl/helpers/defaults.py
hgl/libs/__init__.py
hgl/libs/textures.py
tests/test_extend_context/__init__.py
tests/test_extend_context/test_change_shaders.py
tests/test_extend_context/test_change_vertex_array.py
tests/test_gl_contexts/__init__.py
tests/test_gl_contexts/test_context.py
tests/test_gl_contexts/test_glut.py
tests/test_gl_contexts/test_gtkglarea.py
tests/test_gl_contexts/test_pygame.py