Metadata-Version: 1.0
Name: hgl
Version: 0.1.3
Summary: Simple OpenGL helper library for testing code and writting examples with minimal fuss
Home-page: https://github.com/olymk2/hgl
Author: Oliver Marks
Author-email: oly@digitaloctave.com
License:                     GNU GENERAL PUBLIC LICENSE
